moduleimplant/__init__.py
moduleimplant/modify.py
moduleimplant/moduleimplant.py
moduleimplant-0.2.0.dist-info/LICENSE
moduleimplant-0.2.0.dist-info/METADATA
moduleimplant-0.2.0.dist-info/WHEEL
moduleimplant-0.2.0.dist-info/entry_points.txt
moduleimplant-0.2.0.dist-info/top_level.txt
moduleimplant-0.2.0.dist-info/RECORD
