Metadata-Version: 2.1
Name: moduleimplant
Version: 0.2.0
Summary: A custom module implant system for Ultralytics models
Home-page: https://github.com/Gelinzh/moduleimplant
Author: acelych
Author-email: acelych@foxmail.com
Classifier: Programming Language :: Python :: 3
Classifier: License :: OSI Approved :: MIT License
Classifier: Operating System :: OS Independent
Requires-Python: >=3.9
License-File: LICENSE
Requires-Dist: torch
Requires-Dist: ultralytics
